bitcoin/__init__.py
bitcoin/base58.py
bitcoin/bech32.py
bitcoin/bloom.py
bitcoin/messages.py
bitcoin/net.py
bitcoin/rpc.py
bitcoin/segwit_addr.py
bitcoin/signature.py
bitcoin/signmessage.py
bitcoin/wallet.py
bitcoin/core/__init__.py
bitcoin/core/_bignum.py
bitcoin/core/key.py
bitcoin/core/script.py
bitcoin/core/scripteval.py
bitcoin/core/serialize.py
bitcoin/tests/__init__.py
bitcoin/tests/fakebitcoinproxy.py
bitcoin/tests/test_base58.py
bitcoin/tests/test_bech32.py
bitcoin/tests/test_bloom.py
bitcoin/tests/test_checkblock.py
bitcoin/tests/test_core.py
bitcoin/tests/test_fakebitcoinproxy.py
bitcoin/tests/test_key.py
bitcoin/tests/test_messages.py
bitcoin/tests/test_net.py
bitcoin/tests/test_rpc.py
bitcoin/tests/test_script.py
bitcoin/tests/test_scripteval.py
bitcoin/tests/test_segwit.py
bitcoin/tests/test_serialize.py
bitcoin/tests/test_signmessage.py
bitcoin/tests/test_transactions.py
bitcoin/tests/test_wallet.py
omnicore/__init__.py
omnicore/base58.py
omnicore/bech32.py
omnicore/bloom.py
omnicore/messages.py
omnicore/net.py
omnicore/rpc.py
omnicore/segwit_addr.py
omnicore/signature.py
omnicore/signmessage.py
omnicore/wallet.py
omnicore/core/__init__.py
omnicore/core/_bignum.py
omnicore/core/key.py
omnicore/core/script.py
omnicore/core/scripteval.py
omnicore/core/serialize.py
omnicore/tests/__init__.py
omnicore/tests/fakebitcoinproxy.py
omnicore/tests/test_base58.py
omnicore/tests/test_bech32.py
omnicore/tests/test_bloom.py
omnicore/tests/test_checkblock.py
omnicore/tests/test_core.py
omnicore/tests/test_fakebitcoinproxy.py
omnicore/tests/test_key.py
omnicore/tests/test_messages.py
omnicore/tests/test_net.py
omnicore/tests/test_rpc.py
omnicore/tests/test_script.py
omnicore/tests/test_scripteval.py
omnicore/tests/test_segwit.py
omnicore/tests/test_serialize.py
omnicore/tests/test_signmessage.py
omnicore/tests/test_transactions.py
omnicore/tests/test_wallet.py
python_omnicorelib-0.0.1.dist-info/LICENSE
python_omnicorelib-0.0.1.dist-info/METADATA
python_omnicorelib-0.0.1.dist-info/WHEEL
python_omnicorelib-0.0.1.dist-info/top_level.txt
python_omnicorelib-0.0.1.dist-info/RECORD
