Metadata-Version: 2.1
Name: python-omnicorelib
Version: 0.0.1
Summary: The Swiss Army Knife of the Bitcoin protocol.
Home-page: https://github.com/johng/python-omnicorelib
License: UNKNOWN
Keywords: omnicore
Platform: UNKNOWN
Classifier: Programming Language :: Python
Classifier: License :: OSI Approved :: GNU Lesser General Public License v3 or later (LGPLv3+)
